kuchinawa/Compile.py
kuchinawa/File.py
kuchinawa/Graph.py
kuchinawa/Template.py
kuchinawa/Thread.py
kuchinawa/__init__.py
kuchinawa/Examples/SinCos.py
kuchinawa/Examples/SinCos_ui.py
kuchinawa/Examples/__init__.py
kuchinawa-0.3.dist-info/DESCRIPTION.rst
kuchinawa-0.3.dist-info/METADATA
kuchinawa-0.3.dist-info/RECORD
kuchinawa-0.3.dist-info/WHEEL
kuchinawa-0.3.dist-info/metadata.json
kuchinawa-0.3.dist-info/top_level.txt
