Metadata-Version: 2.0
Name: kuchinawa
Version: 0.3
Summary: Support for creating a control program for measurement instruments
Home-page: https://github.com/threemeninaboat3247/kuchinawa
Author: Yuki Arai
Author-email: threemeninaboat3247@gmail.com
License: MIT
Keywords: measurement
Platform: UNKNOWN
Classifier: Programming Language :: Python :: 3
Classifier: Intended Audience :: Science/Research
Classifier: License :: OSI Approved :: MIT License
Requires-Dist: pandas
Requires-Dist: pyqtgraph (>=0.10.0)
